<?xml version="1.0" encoding="utf-8"?>
<!--
# This file is part of the pl.wrzasq.commons.
#
# @license http://mit-license.org/ The MIT license
# @copyright 2015 - 2016, 2019 © by Rafał Wrzeszcz - Wrzasq.pl.
-->
<project
    xmlns="http://maven.apache.org/DECORATION/1.4.0"
    xmlns:xsi="http://www.w3.org/2001/XMLSchema-instance"
    xsi:schemaLocation="
        http://maven.apache.org/DECORATION/1.4.0 http://maven.apache.org/xsd/decoration-1.4.0.xsd
">
    <body>
        <menu ref="parent"/>

        <menu name="Guide">
            <item name="HTML utilities" href="guide/html-utils.html"/>
            <item name="Text formatter" href="guide/text-formatter.html"/>
            <item name="Slugifier" href="guide/slugifier.html"/>
            <item name="Utils" href="guide/utils.html"/>
        </menu>

        <menu ref="reports"/>
    </body>
</project>
